workday_tools_nosrednakram/RaaSRest.py
workday_tools_nosrednakram/__init__.py
workday_tools_nosrednakram/rest.py
workday_tools-0.1.1.dist-info/licenses/LICENSE
workday_tools-0.1.1.dist-info/WHEEL
workday_tools-0.1.1.dist-info/METADATA
workday_tools-0.1.1.dist-info/RECORD
