Metadata-Version: 2.4
Name: workday_tools
Version: 0.1.1
Summary: Python tools for accessing Workday RaaS endpoints.
Keywords: workday,raas,api,rest
Author-email: Mark W Anderson <nosrednakram@gmail.com>
Requires-Python: >=3.7
Classifier: License :: OSI Approved :: MIT License
Classifier: Programming Language :: Python :: 3
Classifier: Operating System :: OS Independent
License-File: LICENSE
Requires-Dist: requests
Requires-Dist: pyyaml
Requires-Dist: pytest ; extra == "test"
Requires-Dist: pytest-mock ; extra == "test"
Provides-Extra: test
